flexcode/__init__.py
flexcode/_version.py
flexcode/basis_functions.py
flexcode/core.py
flexcode/helpers.py
flexcode/loss_functions.py
flexcode/post_processing.py
flexcode/regression_models.py
flexcode-0.2.2.dist-info/licenses/LICENSE
flexcode-0.2.2.dist-info/METADATA
flexcode-0.2.2.dist-info/WHEEL
flexcode-0.2.2.dist-info/top_level.txt
flexcode-0.2.2.dist-info/RECORD
